{
  "variants": {
    "facing=down": {
      "model": "trainmurdermysteryextras:block/golden_glass_panel_broken",
      "x": 270,
      "uvlock": true
    },
    "facing=east": {
      "model": "trainmurdermysteryextras:block/golden_glass_panel_broken",
      "y": 270,
      "uvlock": true
    },
    "facing=north": {
      "model": "trainmurdermysteryextras:block/golden_glass_panel_broken",
      "y": 180,
      "uvlock": true
    },
    "facing=south": {
      "model": "trainmurdermysteryextras:block/golden_glass_panel_broken",
      "uvlock": true
    },
    "facing=up": {
      "model": "trainmurdermysteryextras:block/golden_glass_panel_broken",
      "x": 90,
      "uvlock": true
    },
    "facing=west": {
      "model": "trainmurdermysteryextras:block/golden_glass_panel_broken",
      "y": 90,
      "uvlock": true
    }
  }
}